seekerfree/__init__.py
seekerfree/seekerfree.cpython-311-linux.so
seekerfree/seekerfree.py
seekerfree/bin/coll
seekerfree/bin/coll-linux
seekerfree/scripts/darwin_seekeragg.sh
seekerfree/scripts/seekeragg.sh
insideopt_dagopt-0.0.1.dist-info/AUTHORS.rst
insideopt_dagopt-0.0.1.dist-info/LICENSE.rst
insideopt_dagopt-0.0.1.dist-info/METADATA
insideopt_dagopt-0.0.1.dist-info/WHEEL
insideopt_dagopt-0.0.1.dist-info/top_level.txt
insideopt_dagopt-0.0.1.dist-info/RECORD
